bumpify/__init__.py
bumpify/context.py
bumpify/core/__init__.py
bumpify/core/api/__init__.py
bumpify/core/api/commands.py
bumpify/core/api/interface.py
bumpify/core/api/presenters.py
bumpify/core/api/providers.py
bumpify/core/config/__init__.py
bumpify/core/config/exc.py
bumpify/core/config/helpers.py
bumpify/core/config/implementation.py
bumpify/core/config/interface.py
bumpify/core/config/objects.py
bumpify/core/console/__init__.py
bumpify/core/console/_message_formatter.py
bumpify/core/console/helpers.py
bumpify/core/console/input.py
bumpify/core/console/interface.py
bumpify/core/console/objects.py
bumpify/core/console/output.py
bumpify/core/filesystem/__init__.py
bumpify/core/filesystem/exc.py
bumpify/core/filesystem/helpers.py
bumpify/core/filesystem/implementation.py
bumpify/core/filesystem/interface.py
bumpify/core/hook/__init__.py
bumpify/core/hook/_utils.py
bumpify/core/hook/decorators.py
bumpify/core/hook/exc.py
bumpify/core/hook/implementation.py
bumpify/core/hook/interface.py
bumpify/core/hook/objects.py
bumpify/core/semver/__init__.py
bumpify/core/semver/_changelog_formatters.py
bumpify/core/semver/_constants.py
bumpify/core/semver/_hook_invokers.py
bumpify/core/semver/_parsing.py
bumpify/core/semver/_version_file_updater.py
bumpify/core/semver/exc.py
bumpify/core/semver/helpers.py
bumpify/core/semver/hooks.py
bumpify/core/semver/implementation.py
bumpify/core/semver/interface.py
bumpify/core/semver/objects.py
bumpify/core/vcs/__init__.py
bumpify/core/vcs/exc.py
bumpify/core/vcs/helpers.py
bumpify/core/vcs/implementation/__init__.py
bumpify/core/vcs/implementation/git.py
bumpify/core/vcs/implementation/proxy.py
bumpify/core/vcs/interface.py
bumpify/core/vcs/objects.py
bumpify/delivery/__init__.py
bumpify/delivery/cli/__init__.py
bumpify/delivery/cli/__main__.py
bumpify/delivery/cli/decorators.py
bumpify/di/__init__.py
bumpify/di/api.py
bumpify/di/config.py
bumpify/di/console.py
bumpify/di/filesystem.py
bumpify/di/hook.py
bumpify/di/semver.py
bumpify-0.5.1.dist-info/METADATA
bumpify-0.5.1.dist-info/WHEEL
bumpify-0.5.1.dist-info/entry_points.txt
bumpify-0.5.1.dist-info/licenses/LICENSE
bumpify-0.5.1.dist-info/RECORD
