Metadata-Version: 2.4
Name: bumpify
Version: 0.5.1
Summary: Semantic versioning automation tool for software projects
License: MIT
License-File: LICENSE
Keywords: semantic,versioning,cli,tool
Author: Maciej Wiatrzyk
Author-email: maciej.wiatrzyk@gmail.com
Requires-Python: >=3.9,<4.0
Classifier: Development Status :: 4 - Beta
Classifier: Environment :: Console
Classifier: Intended Audience :: Developers
Classifier: License :: OSI Approved :: MIT License
Classifier: Programming Language :: Python :: 3
Classifier: Programming Language :: Python :: 3.9
Classifier: Programming Language :: Python :: 3.10
Classifier: Programming Language :: Python :: 3.11
Classifier: Programming Language :: Python :: 3.12
Classifier: Programming Language :: Python :: 3.13
Classifier: Programming Language :: Python :: 3.14
Classifier: Topic :: Utilities
Requires-Dist: click (>=8.1.7,<9.0.0)
Requires-Dist: click-help-colors (>=0.9.4,<0.10.0)
Requires-Dist: colorama (>=0.4.6,<0.5.0)
Requires-Dist: modelity (>=0.26.0,<0.27.0)
Requires-Dist: pydio (>=0.4.1,<0.5.0)
Requires-Dist: tomlkit (>=0.12.4,<0.13.0)
Project-URL: Repository, https://github.com/mwiatrzyk/bumpify
